{"cameraMode":{"drawMode":0,"name":"Shaded","section":"Shading Mode"},"sceneLighting":false,"audioPlay":false,"sceneViewState":{"m_AlwaysRefresh":false,"showFog":true,"showSkybox":false,"showFlares":true,"showImageEffects":true,"showParticleSystems":true,"showVisualEffectGraphs":true,"m_FxEnabled":true},"in2DMode":false,"pivot":{"x":-0.08389019966125488,"y":-0.5757200717926025,"z":0.722278356552124},"rotation":{"x":-0.9614463448524475,"y":0.01017822977155447,"z":0.2726096212863922,"w":0.036085665225982669},"size":0.8660257458686829,"orthographic":false}